CHANGELOG.rst
LICENSE
MANIFEST.in
setup.py
fanyi/__init__.py
fanyi/__main__.py
fanyi/common.py
fanyi/metadata.py
fanyi/textui.py
fanyi.egg-info/PKG-INFO
fanyi.egg-info/SOURCES.txt
fanyi.egg-info/dependency_links.txt
fanyi.egg-info/entry_points.txt
fanyi.egg-info/not-zip-safe
fanyi.egg-info/requires.txt
fanyi.egg-info/top_level.txt
fanyi/services/__init__.py
fanyi/services/iciba.py
fanyi/services/youdao.py